quizmaster/__init__.py
quizmaster/main.py
quizmaster/multiple_choice_question_en.py
quizmaster/multiple_choice_question_es.py
quizmaster/question_en.py
quizmaster/question_es.py
quizmaster/quiz_en.py
quizmaster/quiz_es.py
quizmaster/short_answer_question_en.py
quizmaster/short_answer_question_es.py
quizmaster/single_choice_question_en.py
quizmaster/single_choice_question_es.py
quizmaster/true_false_question_en.py
quizmaster/true_false_question_es.py
question_quizmaster-1.1.dist-info/METADATA
question_quizmaster-1.1.dist-info/WHEEL
question_quizmaster-1.1.dist-info/top_level.txt
question_quizmaster-1.1.dist-info/RECORD
