Metadata-Version: 2.1
Name: question-quizmaster
Version: 1.1
Summary: Create and manage interactive quizzes
Home-page: https://github.com/alaznearamburu/Progra_Grupal4.git
Author: Mikel, Libe, Jon y Alazne
Author-email: alazne.aramburu@alumni.mondragon.edu
Classifier: Programming Language :: Python :: 3
Classifier: License :: OSI Approved :: MIT License
Classifier: Operating System :: OS Independent
Requires-Python: >=3.6
